vrpSolver/__init__.py
vrpSolver/animation.py
vrpSolver/cetsp.py
vrpSolver/color.py
vrpSolver/common.py
vrpSolver/ds.py
vrpSolver/geometry.py
vrpSolver/instance.py
vrpSolver/msg.py
vrpSolver/mtsp.py
vrpSolver/obj2Obj.py
vrpSolver/op.py
vrpSolver/plot.py
vrpSolver/pms.py
vrpSolver/polyTour.py
vrpSolver/province.py
vrpSolver/road.py
vrpSolver/satsp.py
vrpSolver/top.py
vrpSolver/travel.py
vrpSolver/tsp.py
vrpSolver/tsptw.py
vrpSolver/vector.py
vrpSolver/vrptw.py
vrpSolver-0.0.60.dist-info/LICENSE
vrpSolver-0.0.60.dist-info/METADATA
vrpSolver-0.0.60.dist-info/WHEEL
vrpSolver-0.0.60.dist-info/top_level.txt
vrpSolver-0.0.60.dist-info/RECORD
